Metadata-Version: 2.1
Name: twopc
Version: 0.1.0
Summary: A tool for making posterior predicitive checks with 3ML
Home-page: https://github.com/grburgess/twopc
Author: J. Michael Burgess
Author-email: jmichaelburgess@gmail.com
License: GPL-2+
Project-URL: Bug Tracker, https://github.com/grburgess/twopc/issues
Project-URL: Source Code, https://github.com/grburgess/twopc
Platform: UNKNOWN
Classifier: Development Status :: 2 - Pre-Alpha
Classifier: Environment :: Console
Classifier: Intended Audience :: Science/Research
Classifier: License :: OSI Approved :: GNU General Public License v2 or later (GPLv2+)
Classifier: Operating System :: POSIX
Classifier: Programming Language :: Python :: 3.7
Classifier: Programming Language :: Python :: 3.8
